CHANGELOG.md
LICENSE
MANIFEST.in
README.rst
setup.py
docs/.gitkeep
docs/release.rst
teracy/__init__.py
teracy/__init__.pyc
teracy/html5boilerplate/__init__.py
teracy/html5boilerplate/context_processors.py
teracy/html5boilerplate/test_settings.py
teracy/html5boilerplate/urls.py
teracy/html5boilerplate/static/html5boilerplate/apple-touch-icon-precomposed.png
teracy/html5boilerplate/static/html5boilerplate/favicon.ico
teracy/html5boilerplate/static/html5boilerplate/css/main.css
teracy/html5boilerplate/static/html5boilerplate/css/normalize.css
teracy/html5boilerplate/static/html5boilerplate/js/main.js
teracy/html5boilerplate/static/html5boilerplate/js/plugins.js
teracy/html5boilerplate/static/html5boilerplate/js/vendor/jquery-1.10.2.js
teracy/html5boilerplate/static/html5boilerplate/js/vendor/jquery-1.10.2.min.js
teracy/html5boilerplate/static/html5boilerplate/js/vendor/modernizr-2.6.2.js
teracy/html5boilerplate/static/html5boilerplate/js/vendor/modernizr-2.6.2.min.js
teracy/html5boilerplate/templates/html5boilerplate/404.html
teracy/html5boilerplate/templates/html5boilerplate/base.html
teracy/html5boilerplate/templates/html5boilerplate/crossdomain.xml
teracy/html5boilerplate/templates/html5boilerplate/humans.txt
teracy/html5boilerplate/templates/html5boilerplate/robots.txt
teracy/html5boilerplate/tests/__init__.py
teracy/html5boilerplate/tests/context_processors_test.py
teracy_django_html5_boilerplate.egg-info/PKG-INFO
teracy_django_html5_boilerplate.egg-info/SOURCES.txt
teracy_django_html5_boilerplate.egg-info/dependency_links.txt
teracy_django_html5_boilerplate.egg-info/namespace_packages.txt
teracy_django_html5_boilerplate.egg-info/requires.txt
teracy_django_html5_boilerplate.egg-info/top_level.txt