Metadata-Version: 1.1
Name: teracy-django-html5-boilerplate
Version: 0.3.0
Summary: html5-boilerplate Django wrapper application
Home-page: https://github.com/teracy-official/django-html5-boilerplate
Author: hoatle
Author-email: hoatlevan@gmail.com
License: BSD License
Keywords: python,django,html5-boilerplate
Platform: UNKNOWN
Classifier: Development Status :: 2 - Pre-Alpha
Classifier: Environment :: Web Environment
Classifier: Framework :: Django
Classifier: Intended Audience :: Developers
Classifier: License :: OSI Approved
Classifier: License :: OSI Approved :: BSD License
Classifier: Operating System :: OS Independent
Classifier: Programming Language :: Python
Classifier: Programming Language :: Python :: 2.6
Classifier: Programming Language :: Python :: 2.7
Classifier: Programming Language :: Python :: 3.2
Classifier: Programming Language :: Python :: 3.3
Classifier: Topic :: Internet :: WWW/HTTP
Classifier: Topic :: Internet :: WWW/HTTP :: Browsers
